trio_asyncio/__init__.py
trio_asyncio/_adapter.py
trio_asyncio/_async.py
trio_asyncio/_base.py
trio_asyncio/_child.py
trio_asyncio/_deprecate.py
trio_asyncio/_handles.py
trio_asyncio/_loop.py
trio_asyncio/_sync.py
trio_asyncio/_util.py
trio_asyncio/_version.py
trio_asyncio-0.14.1.dist-info/LICENSE
trio_asyncio-0.14.1.dist-info/LICENSE.APACHE2
trio_asyncio-0.14.1.dist-info/LICENSE.MIT
trio_asyncio-0.14.1.dist-info/METADATA
trio_asyncio-0.14.1.dist-info/WHEEL
trio_asyncio-0.14.1.dist-info/top_level.txt
trio_asyncio-0.14.1.dist-info/RECORD
