Metadata-Version: 2.1
Name: trio-asyncio
Version: 0.14.1
Summary: A re-implementation of the asyncio mainloop on top of Trio
Home-page: https://github.com/python-trio/trio-asyncio
Author: Matthias Urlichs
Author-email: matthias@urlichs.de
License: MIT -or- Apache License 2.0
Keywords: async,io,trio,asyncio,trio-asyncio
Classifier: Development Status :: 4 - Beta
Classifier: Intended Audience :: Developers
Classifier: License :: OSI Approved :: MIT License
Classifier: License :: OSI Approved :: Apache Software License
Classifier: Operating System :: POSIX :: Linux
Classifier: Operating System :: MacOS :: MacOS X
Classifier: Operating System :: POSIX :: BSD
Classifier: Operating System :: Microsoft :: Windows
Classifier: Programming Language :: Python :: Implementation :: CPython
Classifier: Programming Language :: Python :: Implementation :: PyPy
Classifier: Programming Language :: Python :: 3 :: Only
Classifier: Programming Language :: Python :: 3.8
Classifier: Programming Language :: Python :: 3.9
Classifier: Programming Language :: Python :: 3.10
Classifier: Programming Language :: Python :: 3.11
Classifier: Programming Language :: Python :: 3.12
Classifier: Topic :: System :: Networking
Classifier: Framework :: Trio
Classifier: Framework :: AsyncIO
Requires-Python: >=3.8
License-File: LICENSE
License-File: LICENSE.APACHE2
License-File: LICENSE.MIT
Requires-Dist: trio >=0.22.0
Requires-Dist: outcome
Requires-Dist: sniffio >=1.3.0
Requires-Dist: greenlet
Requires-Dist: exceptiongroup >=1.0.0 ; python_version < "3.11"
